<annotation>
	<folder>halal</folder>
	<filename>halal_c9.png</filename>
	<path>/Users/liupeng/Documents/GitHub/object_detection_using_tensorflow/images5/halal/halal_c9.png</path>
	<source>
		<database>Unknown</database>
	</source>
	<size>
		<width>504</width>
		<height>320</height>
		<depth>3</depth>
	</size>
	<segmented>0</segmented>
	<object>
		<name>halal</name>
		<pose>Unspecified</pose>
		<truncated>0</truncated>
		<difficult>0</difficult>
		<bndbox>
			<xmin>260</xmin>
			<ymin>193</ymin>
			<xmax>303</xmax>
			<ymax>246</ymax>
		</bndbox>
	</object>
</annotation>
