<annotation>
	<folder>cookies_100g-199g</folder>
	<filename>cookies_100g-199g_e19.png</filename>
	<path>/Users/liupeng/Documents/GitHub/object_detection_using_tensorflow/images5/cookies_100g-199g/cookies_100g-199g_e19.png</path>
	<source>
		<database>Unknown</database>
	</source>
	<size>
		<width>1018</width>
		<height>620</height>
		<depth>3</depth>
	</size>
	<segmented>0</segmented>
	<object>
		<name>cookies_100g-199g</name>
		<pose>Unspecified</pose>
		<truncated>0</truncated>
		<difficult>0</difficult>
		<bndbox>
			<xmin>249</xmin>
			<ymin>172</ymin>
			<xmax>641</xmax>
			<ymax>517</ymax>
		</bndbox>
	</object>
</annotation>
