<annotation>
	<folder>OtherSauceDressing_100-199g_NonHalal_NonHealthy</folder>
	<filename>20240219_12_0429.jpg</filename>
	<path>C:\Users\Mio\Downloads\image_folder_template\OtherSauceDressing_100-199g_NonHalal_NonHealthy\20240219_12_0429.jpg</path>
	<source>
		<database>Unknown</database>
	</source>
	<size>
		<width>1920</width>
		<height>1080</height>
		<depth>3</depth>
	</size>
	<segmented>0</segmented>
	<object>
		<name>OtherSauceDressing_100-199g_NonHalal_NonHealthy</name>
		<pose>Unspecified</pose>
		<truncated>0</truncated>
		<difficult>0</difficult>
		<bndbox>
			<xmin>1074</xmin>
			<ymin>243</ymin>
			<xmax>1233</xmax>
			<ymax>691</ymax>
		</bndbox>
	</object>
</annotation>
