<annotation>
	<folder>Baked beans_400-499g</folder>
	<filename>Baked beans_400-499g_d13.png</filename>
	<path>/Users/liupeng/Documents/GitHub/object_detection_using_tensorflow/images5/Baked beans_400-499g/Baked beans_400-499g_d13.png</path>
	<source>
		<database>Unknown</database>
	</source>
	<size>
		<width>592</width>
		<height>412</height>
		<depth>3</depth>
	</size>
	<segmented>0</segmented>
	<object>
		<name>Baked beans_400-499g</name>
		<pose>Unspecified</pose>
		<truncated>0</truncated>
		<difficult>0</difficult>
		<bndbox>
			<xmin>211</xmin>
			<ymin>113</ymin>
			<xmax>395</xmax>
			<ymax>354</ymax>
		</bndbox>
	</object>
</annotation>
