<annotation>
	<folder>Kitkat</folder>
	<filename>Kitkat_19.png</filename>
	<path>/Users/liupeng/Desktop/research/Object_detection/FoodBankImages/Kitkat/Kitkat_19.png</path>
	<source>
		<database>Unknown</database>
	</source>
	<size>
		<width>604</width>
		<height>896</height>
		<depth>3</depth>
	</size>
	<segmented>0</segmented>
	<object>
		<name>Kitkat</name>
		<pose>Unspecified</pose>
		<truncated>0</truncated>
		<difficult>0</difficult>
		<bndbox>
			<xmin>102</xmin>
			<ymin>134</ymin>
			<xmax>344</xmax>
			<ymax>830</ymax>
		</bndbox>
	</object>
</annotation>
