<annotation>
	<folder>DriedFruits_0-99g_Halal_NonHealthy</folder>
	<filename>20240123_2_2348.jpg</filename>
	<path>C:\Users\Mio\Downloads\image_folder_template\DriedFruits_0-99g_Halal_NonHealthy\20240123_2_2348.jpg</path>
	<source>
		<database>Unknown</database>
	</source>
	<size>
		<width>1620</width>
		<height>1080</height>
		<depth>3</depth>
	</size>
	<segmented>0</segmented>
	<object>
		<name>DriedFruits_0-99g_Halal_NonHealthy</name>
		<pose>Unspecified</pose>
		<truncated>0</truncated>
		<difficult>0</difficult>
		<bndbox>
			<xmin>357</xmin>
			<ymin>279</ymin>
			<xmax>860</xmax>
			<ymax>837</ymax>
		</bndbox>
	</object>
</annotation>
