<?xml version="1.0"?>
<annotation>
	<folder>sardines_100g-199g</folder>
	<filename>sardines_100g-199g_d8.png</filename>
	<path>/Users/liupeng/Documents/GitHub/object_detection_using_tensorflow/images5/sardines_100g-199g/sardines_100g-199g_d8.png</path>
	<source>
		<database>Unknown</database>
	</source>
	<size>
		<width>834</width>
		<height>500</height>
		<depth>3</depth>
	</size>
	<segmented>0</segmented>
	<object>
		<name>sardines_150g</name>
		<pose>Unspecified</pose>
		<truncated>0</truncated>
		<difficult>0</difficult>
		<bndbox>
			<xmin>169</xmin>
			<ymin>46</ymin>
			<xmax>746</xmax>
			<ymax>338</ymax>
		</bndbox>
	</object>
</annotation>
